[
  {
    "slug": "flets-vs-hikari-collabo",
    "title": "フレッツ光 vs 光コラボ、結局どっちが得なの？"
  },
  {
    "slug": "hikari-kodate-hikaku",
    "title": "光回線を戸建てで選ぶなら？おすすめ5選と失敗しない選び方"
  },
  {
    "slug": "hikari-mansion-hikaku",
    "title": "マンションの光回線比較！本当に速くて安いのはどれ？"
  },
  {
    "slug": "hikari-osusume-2026",
    "title": "光回線おすすめ2026年版｜失敗しない選び方と比較"
  },
  {
    "slug": "docomo-hikari-hyoban",
    "title": "ドコモ光の評判は本当？メリット・デメリット全部教えます"
  },
  {
    "slug": "au-hikari-hyoban",
    "title": "auひかりの評判は本当？メリット・デメリット全部教えます"
  },
  {
    "slug": "softbank-hikari-hyoban",
    "title": "ソフトバンク光の評判は本当？メリット・デメリット全解説"
  },
  {
    "slug": "nuro-hikari-hyoban",
    "title": "NURO光の評判は本当に遅い？速い？真実を解説"
  },
  {
    "slug": "rakuten-hikari-hyoban",
    "title": "楽天ひかりの評判は本当？メリット・デメリット全部教えます"
  },
  {
    "slug": "hikari-kouji-fuyou",
    "title": "光回線で工事不要のおすすめ5選！失敗しない選び方"
  },
  {
    "slug": "home-router-osusume-2026",
    "title": "ホームルーターおすすめ2026年版｜失敗しない5選と選び方"
  },
  {
    "slug": "wimax-vs-hikari",
    "title": "WiMAXと光回線どっちがいい？10年使い比べた結論"
  },
  {
    "slug": "hikari-smartphone-set",
    "title": "光回線×スマホセット割おすすめ比較2026年版"
  },
  {
    "slug": "hikari-norikae-tejun",
    "title": "光回線の乗り換え手順と違約金の全知識【失敗ゼロ】"
  }
]